<root type='CompilationUnit'><packageDeclaration type='PackageDeclaration'><name type='Name' identifier='image'><qualifier type='Name' identifier='internal'><qualifier type='Name' identifier='swt'><qualifier type='Name' identifier='eclipse'><qualifier type='Name' identifier='org'></qualifier></qualifier></qualifier></qualifier></name></packageDeclaration><comment type='JavadocComment' content=' Copyright c 2000 2003 IBM Corporation and others All rights reserved This program and the accompanying materials are made available under the terms of the Eclipse Public License v1 0 which accompanies this distribution and is available at http www eclipse org legal epl v10 html Contributors IBM Corporation initial API and implementation '></comment><types><type type='ClassOrInterfaceDeclaration' isInterface='false'><name type='SimpleName' identifier='JPEGAppn'></name><extendedTypes><extendedType type='ClassOrInterfaceType'><name type='SimpleName' identifier='JPEGVariableSizeSegment'></name></extendedType></extendedTypes><members><member type='ConstructorDeclaration'><body type='BlockStmt'><statements><statement type='ExplicitConstructorInvocationStmt' isThis='false'><arguments><argument type='NameExpr'><name type='SimpleName' identifier='reference'></name></argument></arguments></statement></statements></body><name type='SimpleName' identifier='JPEGAppn'></name><modifiers><modifier type='Modifier' keyword='PUBLIC'></modifier></modifiers><parameters><parameter type='Parameter' isVarArgs='false'><name type='SimpleName' identifier='reference'></name><type type='ArrayType' origin='TYPE'><componentType type='PrimitiveType' specificType='BYTE'></componentType></type></parameter></parameters></member><member type='ConstructorDeclaration'><body type='BlockStmt'><statements><statement type='ExplicitConstructorInvocationStmt' isThis='false'><arguments><argument type='NameExpr'><name type='SimpleName' identifier='byteStream'></name></argument></arguments></statement></statements></body><name type='SimpleName' identifier='JPEGAppn'></name><modifiers><modifier type='Modifier' keyword='PUBLIC'></modifier></modifiers><parameters><parameter type='Parameter' isVarArgs='false'><name type='SimpleName' identifier='byteStream'></name><type type='ClassOrInterfaceType'><name type='SimpleName' identifier='LEDataInputStream'></name></type></parameter></parameters></member><member type='MethodDeclaration'><body type='BlockStmt'><statements><statement type='ExpressionStmt'><expression type='VariableDeclarationExpr'><variables><variable type='VariableDeclarator'><initializer type='MethodCallExpr'><name type='SimpleName' identifier='getSegmentMarker'></name></initializer><name type='SimpleName' identifier='marker'></name><type type='PrimitiveType' specificType='INT'></type></variable></variables></expression></statement><statement type='ReturnStmt'><expression type='BinaryExpr' operator='AND'><left type='BinaryExpr' operator='GREATER EQUALS'><left type='NameExpr'><name type='SimpleName' identifier='marker'></name></left><right type='FieldAccessExpr'><name type='SimpleName' identifier='APP0'></name><scope type='NameExpr'><name type='SimpleName' identifier='JPEGFileFormat'></name></scope></right></left><right type='BinaryExpr' operator='LESS EQUALS'><left type='NameExpr'><name type='SimpleName' identifier='marker'></name></left><right type='FieldAccessExpr'><name type='SimpleName' identifier='APP15'></name><scope type='NameExpr'><name type='SimpleName' identifier='JPEGFileFormat'></name></scope></right></right></expression></statement></statements></body><type type='PrimitiveType' specificType='BOOLEAN'></type><name type='SimpleName' identifier='verify'></name><modifiers><modifier type='Modifier' keyword='PUBLIC'></modifier></modifiers></member></members><modifiers><modifier type='Modifier' keyword='FINAL'></modifier></modifiers></type></types></root>
